sagemaker_studio_boto3_plugin/__init__.py
sagemaker_studio_boto3_plugin-0.0.1.dist-info/METADATA
sagemaker_studio_boto3_plugin-0.0.1.dist-info/WHEEL
sagemaker_studio_boto3_plugin-0.0.1.dist-info/top_level.txt
sagemaker_studio_boto3_plugin-0.0.1.dist-info/RECORD
