Metadata-Version: 2.4
Name: sagemaker_studio_boto3_plugin
Version: 0.0.1
Summary: SageMaker Studio Boto3 Plugin
Author: Amazon Web Services
Requires-Python: >=3.9
Provides-Extra: test
Requires-Dist: pytest; extra == "test"
Requires-Dist: pytest-cov; extra == "test"
Requires-Dist: toml; extra == "test"
Requires-Dist: coverage; extra == "test"
Provides-Extra: dev
Requires-Dist: wheel; extra == "dev"
Requires-Dist: invoke; extra == "dev"
Requires-Dist: twine; extra == "dev"
Dynamic: author
Dynamic: description
Dynamic: description-content-type
Dynamic: provides-extra
Dynamic: requires-python
Dynamic: summary
